caesar_pompey/__init__.py
caesar_pompey/caesar.py
caesar_pompey/pompey.py
caesar_pompey/utils.py
caesar_pompey-0.0.3.dist-info/entry_points.txt
caesar_pompey-0.0.3.dist-info/LICENSE
caesar_pompey-0.0.3.dist-info/WHEEL
caesar_pompey-0.0.3.dist-info/METADATA
caesar_pompey-0.0.3.dist-info/RECORD
